tessie_api/__init__.py
tessie_api/battery.py
tessie_api/battery_health.py
tessie_api/boombox.py
tessie_api/charges.py
tessie_api/charging.py
tessie_api/climate.py
tessie_api/current_state.py
tessie_api/doors.py
tessie_api/drives.py
tessie_api/historical_states.py
tessie_api/homelink.py
tessie_api/horn.py
tessie_api/idles.py
tessie_api/keyless_driving.py
tessie_api/lights.py
tessie_api/literals.py
tessie_api/scheduling.py
tessie_api/sentry_mode.py
tessie_api/share.py
tessie_api/software.py
tessie_api/speed_limit.py
tessie_api/status.py
tessie_api/sunroof.py
tessie_api/tessie_wrapper.py
tessie_api/tire_pressure.py
tessie_api/trunks.py
tessie_api/valet_mode.py
tessie_api/wake.py
tessie_api/windows.py
tessie_api-0.1.2.dist-info/METADATA
tessie_api-0.1.2.dist-info/WHEEL
tessie_api-0.1.2.dist-info/licenses/LICENSE
tessie_api-0.1.2.dist-info/RECORD
