Metadata-Version: 2.4
Name: tessie_api
Version: 0.1.2
Summary: A small python package that wraps up the Tessie API 
Project-URL: Homepage, https://github.com/andrewgierens/tessie_python_api
Project-URL: Bug Tracker, https://github.com/andrewgierens/tessie_python_api/issues
Author-email: Andrew Gierens <apgierens@gmail.com>
License-File: LICENSE
Classifier: License :: OSI Approved :: GNU General Public License v3 (GPLv3)
Classifier: Operating System :: OS Independent
Classifier: Programming Language :: Python :: 3
Requires-Python: >=3.5
